{
  "job": "repair_final_readme_02",
  "provider": "Mistral Cloud",
  "model": "mistral-medium-3.5",
  "started_utc": "2026-07-18T19:05:20.014540+00:00",
  "finished_utc": "2026-07-18T19:06:19.051325+00:00",
  "duration_seconds": 59.037,
  "inputs": [
    {
      "path": ".orchestration\\prompts\\repair_final_readme_02.md",
      "sha256": "55ce6c2816c0be7fcf4d54b5b201c88ed603f54d63ced73e49d576849328122c"
    },
    {
      "path": "README.md",
      "sha256": "d0a43b1acb123ac6b7d46bf64fefcea26148563c52951f9ef3100038050199e2"
    }
  ],
  "output": {
    "path": "README.md",
    "bytes": 6911,
    "sha256": "b96075d93ea946f1c08d2e2440810ef6e23c68bdd35245b5a2bff5727b94a853"
  },
  "usage": {},
  "command_policy": {
    "tools": "disabled",
    "max_price_usd": 0.4
  }
}
